top_manav/__init__.py
top_manav/topsis_manav.py
Topsis_manav-0.0.1.dist-info/LICENSE
Topsis_manav-0.0.1.dist-info/METADATA
Topsis_manav-0.0.1.dist-info/WHEEL
Topsis_manav-0.0.1.dist-info/top_level.txt
Topsis_manav-0.0.1.dist-info/RECORD
