Metadata-Version: 2.1
Name: Topsis-manav
Version: 0.0.1
Summary: A python package to implement Topsis approach
Home-page: https://github.com/pypa/Topsis
Author: Manavbir singh gill
Author-email: mgill_be17@thapar.edu
License: UNKNOWN
Platform: UNKNOWN
Classifier: Programming Language :: Python :: 3
Classifier: License :: OSI Approved :: MIT License
Classifier: Operating System :: OS Independent
Requires-Python: >=3
Requires-Dist: requests
